cciic/__init__.py
cciic/__main__.py
cciic/momo_display.py
cciic/player.py
cciic/assets/images/6817ae5e5cb2biLo.gif
cciic/assets/images/6817ae5e76935ahN.gif
cciic/assets/images/6817ae5e92f62efF.gif
cciic/assets/images/6817ae5eae2e152j.gif
cciic/assets/images/6817ae5eca8101pp.gif
cciic/assets/images/6817ae5f1e183xax.gif
cciic/assets/images/6817ae5f86565Ba6.gif
cciic/assets/images/6817ae5fa1cacwN1.gif
cciic/assets/music/蓝莲哈.mp3
cciic-0.1.0.dist-info/METADATA
cciic-0.1.0.dist-info/WHEEL
cciic-0.1.0.dist-info/entry_points.txt
cciic-0.1.0.dist-info/top_level.txt
cciic-0.1.0.dist-info/RECORD
